[
  {"年份":1994,"奖项":"美国奥斯卡金像奖","类别":"最佳男配角","结果":"提名","电影":"《燃情岁月》"},
  {"年份":1994,"奖项":"MTV电影大奖","类别":"最佳突破男演员","结果":"获奖","电影":"《燃情岁月》"},
  {"年份":1994,"奖项":"芝加哥影评人协会奖","类别":"最有潜力演员","结果":"获奖","电影":"《燃情岁月》"},
  {"年份":1994,"奖项":"国家评论委员会奖","类别":"最佳男配角","结果":"获奖","电影":"《燃情岁月》"},
  {"年份":1994,"奖项":"青少年艺术家奖","类别":"最佳青年男配角","结果":"提名","电影":"《篮球日记》"},
  {"年份":1997,"奖项":"青少年艺术家奖","类别":"最佳青年男配角","结果":"提名","电影":"《篮球日记》"},
  {"年份":1998,"奖项":"美国金球奖","类别":"剧情类最佳男主角","结果":"提名","电影":"《泰坦尼克号》"},
  {"年份":1998,"奖项":"MTV电影大奖","类别":"最佳男演员","结果":"提名","电影":"《泰坦尼克号》"},
  {"年份":2000,"奖项":"MTV电影大奖","类别":"最佳男演员","结果":"获奖","电影":"《海滩》"},
  {"年份":2002,"奖项":"帝国电影奖","类别":"最佳男演员","结果":"提名","电影":"《纽约黑帮》"},
  {"年份":2003,"奖项":"美国金球奖","类别":"剧情类最佳男主角","结果":"提名","电影":"《猫鼠游戏》"},
  {"年份":2003,"奖项":"MTV电影大奖","类别":"最佳男演员","结果":"提名","电影":"《猫鼠游戏》"},
  {"年份":2005,"奖项":"美国奥斯卡金像奖","类别":"最佳男主角","结果":"提名","电影":"《飞行者》"},
  {"年份":2005,"奖项":"美国金球奖","类别":"剧情类最佳男主角","结果":"获奖","电影":"《飞行者》"},
  {"年份":2005,"奖项":"MTV电影大奖","类别":"最佳男演员","结果":"获奖","电影":"《飞行者》"},
  {"年份":2005,"奖项":"影评人选择电影奖","类别":"最佳男主角","结果":"获奖","电影":"《飞行者》"},
  {"年份":2007,"奖项":"美国金球奖","类别":"剧情类最佳男主角","结果":"提名","电影":"《血钻》"},
  {"年份":2007,"奖项":"美国奥斯卡金像奖","类别":"最佳男主角","结果":"提名","电影":"《血钻》"},
  {"年份":2007,"奖项":"MTV电影大奖","类别":"最佳男演员","结果":"提名","电影":"《血钻》"},
  {"年份":2007,"奖项":"帝国电影奖","类别":"最佳男演员","结果":"提名","电影":"《血钻》"},
  {"年份":2012,"奖项":"美国金球奖","类别":"最佳男配角","结果":"提名","电影":"《被解救的姜戈》"},
  {"年份":2014,"奖项":"美国奥斯卡金像奖","类别":"最佳男主角","结果":"提名","电影":"《华尔街之狼》"},
  {"年份":2014,"奖项":"美国奥斯卡金像奖","类别":"最佳影片","结果":"提名","电影":"《华尔街之狼》"},
  {"年份":2014,"奖项":"美国金球奖","类别":"音乐或喜剧类最佳男主角","结果":"获奖","电影":"《华尔街之狼》"},
  {"年份":2014,"奖项":"MTV电影大奖","类别":"最佳男演员","结果":"提名","电影":"《华尔街之狼》"},
  {"年份":2014,"奖项":"影评人选择电影奖","类别":"最佳男主角","结果":"提名","电影":"《华尔街之狼》"},
  {"年份":2014,"奖项":"金卫星奖","类别":"喜剧或音乐类最佳男主角","结果":"提名","电影":"《华尔街之狼》"},
  {"年份":2014,"奖项":"伦敦影评人协会奖","类别":"年度最佳男演员","结果":"提名","电影":"《华尔街之狼》"},
  {"年份":2014,"奖项":"国家评论委员会奖","类别":"最佳男主角","结果":"提名","电影":"《华尔街之狼》"},
  {"年份":2014,"奖项":"纽约影评人协会奖","类别":"最佳男主角","结果":"提名","电影":"《华尔街之狼》"},
  {"年份":2014,"奖项":"在线影评人协会奖","类别":"最佳男主角","结果":"提名","电影":"《华尔街之狼》"},
  {"年份":2016,"奖项":"美国奥斯卡金像奖","类别":"最佳男主角","结果":"获奖","电影":"《荒野猎人》"},
  {"年份":2016,"奖项":"美国金球奖","类别":"剧情类最佳男主角","结果":"获奖","电影":"《荒野猎人》"},
  {"年份":2016,"奖项":"英国电影和电视艺术学院奖（BAFTA）","类别":"最佳男主角","结果":"获奖","电影":"《荒野猎人》"},
  {"年份":2016,"奖项":"MTV电影大奖","类别":"最佳男演员","结果":"获奖","电影":"《荒野猎人》"},
  {"年份":2016,"奖项":"影评人选择电影奖","类别":"最佳男主角","结果":"获奖","电影":"《荒野猎人》"},
  {"年份":2016,"奖项":"金卫星奖","类别":"剧情类最佳男主角","结果":"获奖","电影":"《荒野猎人》"},
  {"年份":2016,"奖项":"伦敦影评人协会奖","类别":"年度最佳男演员","结果":"获奖","电影":"《荒野猎人》"},
  {"年份":2016,"奖项":"国家评论委员会奖","类别":"最佳男主角","结果":"获奖","电影":"《荒野猎人》"},
  {"年份":2016,"奖项":"纽约影评人协会奖","类别":"最佳男主角","结果":"获奖","电影":"《荒野猎人》"},
  {"年份":2016,"奖项":"在线影评人协会奖","类别":"最佳男主角","结果":"获奖","电影":"《荒野猎人》"},
  {"年份":2016,"奖项":"帝国电影奖","类别":"最佳男演员","结果":"获奖","电影":"《荒野猎人》"},
  {"年份":2016,"奖项":"圣巴巴拉国际电影节","类别":"杰出演员奖","结果":"获奖","电影":"《荒野猎人》"},
  {"年份":2020,"奖项":"美国奥斯卡金像奖","类别":"最佳男主角","结果":"提名","电影":"《好莱坞往事》"},
  {"年份":2020,"奖项":"美国金球奖","类别":"音乐或喜剧类最佳男主角","结果":"提名","电影":"《好莱坞往事》"},
  {"年份":2020,"奖项":"英国电影和电视艺术学院奖（BAFTA）","类别":"最佳男主角","结果":"提名","电影":"《好莱坞往事》"},
  {"年份":2021,"奖项":"美国演员工会奖（SAG）","类别":"电影类最佳男主角","结果":"提名","电影":"《好莱坞往事》"}
]

